clamlite/__init__.py
clamlite/create_patches_fp.py
clamlite/extract_features_fp.py
clamlite/dataset_modules/__init__.py
clamlite/dataset_modules/dataset_generic.py
clamlite/dataset_modules/dataset_h5.py
clamlite/dataset_modules/wsi_dataset.py
clamlite/models/__init__.py
clamlite/models/builder.py
clamlite/models/resnet_custom_dep.py
clamlite/models/timm_wrapper.py
clamlite/utils/__init__.py
clamlite/utils/constants.py
clamlite/utils/core_utils.py
clamlite/utils/eval_utils.py
clamlite/utils/file_utils.py
clamlite/utils/transform_utils.py
clamlite/utils/utils.py
clamlite/wsi_core/WholeSlideImage.py
clamlite/wsi_core/__init__.py
clamlite/wsi_core/batch_process_utils.py
clamlite/wsi_core/util_classes.py
clamlite/wsi_core/wsi_utils.py
clamlite-0.0.4.dist-info/LICENSE.md
clamlite-0.0.4.dist-info/METADATA
clamlite-0.0.4.dist-info/WHEEL
clamlite-0.0.4.dist-info/top_level.txt
clamlite-0.0.4.dist-info/RECORD
