Metadata-Version: 2.1
Name: clamlite
Version: 0.0.4
Author-email: Richard Chen <richen1939@gmail.com>, "Ming Y. Lu" <mingylu@mit.edu>
Requires-Python: >=3.9
License-File: LICENSE.md
Requires-Dist: timm >=0.9.8
Requires-Dist: torch
Requires-Dist: torchvision
Requires-Dist: h5py
Requires-Dist: pandas
Requires-Dist: PyYAML
Requires-Dist: opencv-python
Requires-Dist: matplotlib
Requires-Dist: scikit-learn
Requires-Dist: scipy
Requires-Dist: tqdm
Requires-Dist: openslide-python
Requires-Dist: tensorboardX
